dvadmin_upgrade_center/__init__.py
dvadmin_upgrade_center/apps.py
dvadmin_upgrade_center/init_data.py
dvadmin_upgrade_center/initialize.py
dvadmin_upgrade_center/models.py
dvadmin_upgrade_center/settings.py
dvadmin_upgrade_center/urls.py
dvadmin_upgrade_center/fixtures/__init__.py
dvadmin_upgrade_center/fixtures/initialize.py
dvadmin_upgrade_center/migrations/0001_initial.py
dvadmin_upgrade_center/migrations/__init__.py
dvadmin_upgrade_center/views/__init__.py
dvadmin_upgrade_center/views/app_device_manage.py
dvadmin_upgrade_center/views/app_version.py
dvadmin_upgrade_center/views/app_version_back.py
dvadmin_upgrade_center/views/application.py
dvadmin_upgrade_center/views/device_upgrade.py
dvadmin_upgrade_center/views/upgrade_logging.py
dvadmin_upgrade_center-1.0.2.dist-info/LICENSE
dvadmin_upgrade_center-1.0.2.dist-info/METADATA
dvadmin_upgrade_center-1.0.2.dist-info/WHEEL
dvadmin_upgrade_center-1.0.2.dist-info/top_level.txt
dvadmin_upgrade_center-1.0.2.dist-info/RECORD
