Metadata-Version: 2.1
Name: dvadmin-upgrade-center
Version: 1.0.2
Summary: 适用用 django-vue-admin 的升级中心后端插件
Home-page: https://gitee.com/huge-dream/dvadmin-upgrade-center
Author: DVAdmin
Author-email: liqiang@django-vue-admin.com
Classifier: Programming Language :: Python :: 3
Classifier: License :: OSI Approved :: MIT License
Classifier: Operating System :: OS Independent
Requires-Python: >=3.7, <4
License-File: LICENSE
